{"cameraMode":{"drawMode":0,"name":"Shaded","section":"Shading Mode"},"sceneLighting":false,"audioPlay":false,"sceneViewState":{"showFog":true,"showMaterialUpdate":false,"showSkybox":false,"showFlares":true,"showImageEffects":true,"showParticleSystems":true},"in2DMode":false,"pivot":{"x":-0.04936961829662323,"y":0.10012086480855942,"z":0.1562182903289795},"rotation":{"x":-0.029807230457663537,"y":0.3484458327293396,"z":-0.011092612519860268,"w":-0.9367967844009399},"size":0.7202994227409363,"orthographic":false}